chattin/__init__.py
chattin-0.0.1.dist-info/WHEEL
chattin-0.0.1.dist-info/METADATA
chattin-0.0.1.dist-info/RECORD
